gtirb_capstone/__init__.py
gtirb_capstone/instructions.py
gtirb_capstone/rewriting.py
gtirb_capstone/version.py
gtirb_capstone/x86.py
gtirb_capstone-1.0.2.dist-info/LICENSE.txt
gtirb_capstone-1.0.2.dist-info/METADATA
gtirb_capstone-1.0.2.dist-info/WHEEL
gtirb_capstone-1.0.2.dist-info/top_level.txt
gtirb_capstone-1.0.2.dist-info/RECORD
