Metadata-Version: 2.1
Name: gtirb-capstone
Version: 1.0.2
Summary: Utilities for rewriting GTIRB with capstone and keystone
Home-page: https://github.com/grammatech/gtirb-functions
Author: Grammatech
Author-email: gtirb@grammatech.com
License: MIT
Platform: UNKNOWN
Classifier: Programming Language :: Python :: 3
License-File: LICENSE.txt
Requires-Dist: capstone-gt
Requires-Dist: gtirb
Requires-Dist: keystone-engine
Requires-Dist: dataclasses ; python_version < "3.7.0"
Provides-Extra: test
Requires-Dist: flake8 ; extra == 'test'
Requires-Dist: isort ; extra == 'test'
Requires-Dist: pytest ; extra == 'test'
Requires-Dist: pytest-cov ; extra == 'test'
Requires-Dist: tox ; extra == 'test'
Requires-Dist: tox-wheel ; extra == 'test'
Requires-Dist: pre-commit ; extra == 'test'
Requires-Dist: mcasm ~=0.1.0 ; extra == 'test'
